Workbook

Sheet Business Data
A1: Month | B1: Revenue (₦) | C1: Expenses (₦) | D1: Profit (₦) | E1: Customers | F1: Orders | G1: Profit Margin
A2: Jan | B2: 1850000 | C2: 1210000 | D2: =B2-C2 | E2: 142 | F2: 196 | G2: =D2/B2
A3: Feb | B3: 2010000 | C3: 1280000 | D3: =B3-C3 | E3: 151 | F3: 211 | G3: =D3/B3
A4: Mar | B4: 1940000 | C4: 1260000 | D4: =B4-C4 | E4: 148 | F4: 205 | G4: =D4/B4
A5: Apr | B5: 2230000 | C5: 1390000 | D5: =B5-C5 | E5: 165 | F5: 229 | G5: =D5/B5
A6: May | B6: 2380000 | C6: 1450000 | D6: =B6-C6 | E6: 173 | F6: 241 | G6: =D6/B6
A7: Jun | B7: 2510000 | C7: 1510000 | D7: =B7-C7 | E7: 181 | F7: 253 | G7: =D7/B7
A8: Jul | B8: 2440000 | C8: 1490000 | D8: =B8-C8 | E8: 178 | F8: 249 | G8: =D8/B8
A9: Aug | B9: 2690000 | C9: 1580000 | D9: =B9-C9 | E9: 194 | F9: 272 | G9: =D9/B9
A10: Sep | B10: 2810000 | C10: 1660000 | D10: =B10-C10 | E10: 205 | F10: 288 | G10: =D10/B10
A11: Oct | B11: 2960000 | C11: 1740000 | D11: =B11-C11 | E11: 214 | F11: 301 | G11: =D11/B11
A12: Nov | B12: 3150000 | C12: 1810000 | D12: =B12-C12 | E12: 228 | F12: 319 | G12: =D12/B12
A13: Dec | B13: 3380000 | C13: 1900000 | D13: =B13-C13 | E13: 241 | F13: 338 | G13: =D13/B13

Sheet Dashboard
A1: BUSINESS PERFORMANCE DASHBOARD
A3: KPI | B3: Value | D3: Month | E3: Revenue | F3: Profit | G3: Margin | I3: Management Insights
A4: Annual Revenue | B4: =SUM('Business Data'!B2:B13) | D4: ='Business Data'!A2 | E4: ='Business Data'!B2 | F4: ='Business Data'!D2 | G4: ='Business Data'!G2 | I4: Revenue and profit trend upward across the year.
A5: Annual Expenses | B5: =SUM('Business Data'!C2:C13) | D5: ='Business Data'!A3 | E5: ='Business Data'!B3 | F5: ='Business Data'!D3 | G5: ='Business Data'!G3 | I5: Monitor expense growth so it does not outpace revenue.
A6: Annual Profit | B6: =SUM('Business Data'!D2:D13) | D6: ='Business Data'!A4 | E6: ='Business Data'!B4 | F6: ='Business Data'!D4 | G6: ='Business Data'!G4 | I6: Customer and order growth suggests improving demand.
A7: Average Monthly Revenue | B7: =AVERAGE('Business Data'!B2:B13) | D7: ='Business Data'!A5 | E7: ='Business Data'!B5 | F7: ='Business Data'!D5 | G7: ='Business Data'!G5 | I7: Use monthly KPIs to identify strong periods and investigate weaker ones.
A8: Average Monthly Profit | B8: =AVERAGE('Business Data'!D2:D13) | D8: ='Business Data'!A6 | E8: ='Business Data'!B6 | F8: ='Business Data'!D6 | G8: ='Business Data'!G6 | I8: Data is simulated for portfolio demonstration.
A9: Total Customers | B9: =SUM('Business Data'!E2:E13) | D9: ='Business Data'!A7 | E9: ='Business Data'!B7 | F9: ='Business Data'!D7 | G9: ='Business Data'!G7
A10: Total Orders | B10: =SUM('Business Data'!F2:F13) | D10: ='Business Data'!A8 | E10: ='Business Data'!B8 | F10: ='Business Data'!D8 | G10: ='Business Data'!G8
A11: Annual Profit Margin | B11: =SUM('Business Data'!D2:D13)/SUM('Business Data'!B2:B13) | D11: ='Business Data'!A9 | E11: ='Business Data'!B9 | F11: ='Business Data'!D9 | G11: ='Business Data'!G9
D12: ='Business Data'!A10 | E12: ='Business Data'!B10 | F12: ='Business Data'!D10 | G12: ='Business Data'!G10
D13: ='Business Data'!A11 | E13: ='Business Data'!B11 | F13: ='Business Data'!D11 | G13: ='Business Data'!G11
D14: ='Business Data'!A12 | E14: ='Business Data'!B12 | F14: ='Business Data'!D12 | G14: ='Business Data'!G12
D15: ='Business Data'!A13 | E15: ='Business Data'!B13 | F15: ='Business Data'!D13 | G15: ='Business Data'!G13
